pytabula/__init__.py
pytabula/abc.py
pytabula/table.py
pytabula-0.3.0.dist-info/LICENSE
pytabula-0.3.0.dist-info/METADATA
pytabula-0.3.0.dist-info/WHEEL
pytabula-0.3.0.dist-info/RECORD
