Metadata-Version: 2.1
Name: pytabula
Version: 0.3.0
Summary: A minimal Python table extension
Home-page: https://genadijrazdorov.github.io/pytabula/
License: MIT
Author: Genadij Razdorov
Author-email: genadijrazdorov@gmail.com
Requires-Python: >=3.11,<4.0
Classifier: License :: OSI Approved :: MIT License
Classifier: Programming Language :: Python :: 3
Classifier: Programming Language :: Python :: 3.11
Project-URL: Repository, https://github.com/genadijrazdorov/pytabula
